structlog_cloudrun/__init__.py
structlog_cloudrun-0.2.0.dist-info/METADATA
structlog_cloudrun-0.2.0.dist-info/WHEEL
structlog_cloudrun-0.2.0.dist-info/licenses/LICENSE
structlog_cloudrun-0.2.0.dist-info/RECORD
