Metadata-Version: 2.4
Name: structlog-cloudrun
Version: 0.2.0
Summary: A structlog processor for Google Cloud Run logging.
Project-URL: Homepage, https://github.com/turisesonia/structlog-cloudrun
Project-URL: Repository, https://github.com/turisesonia/structlog-cloudrun
Project-URL: Issues, https://github.com/turisesonia/structlog-cloudrun/issues
Author-email: Sam Yao <turisesonia@gmail.com>
License: MIT
License-File: LICENSE
Keywords: cloud-run,gcp,google-cloud,logging,structlog
Classifier: Development Status :: 4 - Beta
Classifier: Intended Audience :: Developers
Classifier: License :: OSI Approved :: MIT License
Classifier: Operating System :: OS Independent
Classifier: Programming Language :: Python :: 3
Classifier: Programming Language :: Python :: 3.11
Classifier: Programming Language :: Python :: 3.12
Classifier: Programming Language :: Python :: 3.13
Classifier: Topic :: Software Development :: Libraries :: Python Modules
Classifier: Topic :: System :: Logging
Requires-Python: >=3.11
Requires-Dist: structlog>=25.0.0
